{
  "run_id": "run_20260712_010103",
  "timestamp": "20260712_010103",
  "metadata": {
    "image_path": "/Users/yashpatel/Desktop/PROJECTS/Rice Analyzer/uploads/upload_20260712_011321_877261_WhatsApp Image 2026-07-12 at 01.12.13.jpeg",
    "image_shape": [
      683,
      1024,
      3
    ],
    "analysis_time": "2026-07-12T01:13:23.853876",
    "calibrated": true,
    "pixels_per_mm": 1000.0,
    "use_watershed": true
  },
  "measurements": [
    {
      "label": 1,
      "area_px": 62.0,
      "area_mm2": 6.2e-05,
      "hull_area_px": 63.5,
      "hull_area_mm2": 6.35e-05,
      "perimeter_px": 30.14213526248932,
      "perimeter_mm": 0.03014213526248932,
      "hull_perimeter_px": 29.607698678970337,
      "hull_perimeter_mm": 0.029607698678970337,
      "length_px": 10.0,
      "length_mm": 0.01,
      "width_px": 8.0,
      "width_mm": 0.008,
      "major_axis_px": 10.0,
      "major_axis_mm": 0.01,
      "minor_axis_px": 8.0,
      "minor_axis_mm": 0.008,
      "bbox_x": 12,
      "bbox_y": 397,
      "bbox_w_px": 11,
      "bbox_h_px": 9,
      "bbox_w_mm": 0.011,
      "bbox_h_mm": 0.009,
      "rot_rect_w_px": 8.0,
      "rot_rect_h_px": 10.0,
      "rot_rect_w_mm": 0.008,
      "rot_rect_h_mm": 0.01,
      "rot_rect_angle": -90.0,
      "solidity": 0.9763779527559056,
      "convexity": 0.9822694517536696,
      "circularity": 0.8575382976318751,
      "elongation": 0.8,
      "aspect_ratio": 1.25,
      "eccentricity": 0.5511943743803066,
      "extent": 0.6262626262626263,
      "fill_ratio": 0.775,
      "equivalent_diameter_px": 8.884866446580956,
      "equivalent_diameter_mm": 0.008884866446580956,
      "feret_max_px": 10.367128372192383,
      "feret_max_mm": 0.010367128372192383,
      "feret_min_px": 8.650092124938965,
      "feret_min_mm": 0.008650092124938965,
      "centroid_x": 17.276881720430104,
      "centroid_y": 401.44086021505376,
      "orientation_angle": 103.47913360595703,
      "hu_moments": [
        0.15534589612971875,
        0.0013419794118379549,
        0.0004667897680209661,
        3.9377899336477435e-06,
        -7.845551906146595e-11,
        -6.499046095060028e-08,
        1.495118428650084e-10
      ],
      "zernike_moments": [
        1.0,
        0.6042082989556272,
        0.4144179138581051,
        0.3060583234412771,
        0.2375485926001776
      ]
    },
    {
      "label": 2,
      "area_px": 61.5,
      "area_mm2": 6.15e-05,
      "hull_area_px": 70.5,
      "hull_area_mm2": 7.05e-05,
      "perimeter_px": 39.21320307254791,
      "perimeter_mm": 0.039213203072547914,
      "hull_perimeter_px": 36.85453534126282,
      "hull_perimeter_mm": 0.03685453534126282,
      "length_px": 14.758047103881836,
      "length_mm": 0.014758047103881835,
      "width_px": 5.81377649307251,
      "width_mm": 0.00581377649307251,
      "major_axis_px": 14.758047103881836,
      "major_axis_mm": 0.014758047103881835,
      "minor_axis_px": 5.81377649307251,
      "minor_axis_mm": 0.00581377649307251,
      "bbox_x": 3,
      "bbox_y": 634,
      "bbox_w_px": 16,
      "bbox_h_px": 10,
      "bbox_w_mm": 0.016,
      "bbox_h_mm": 0.01,
      "rot_rect_w_px": 14.758047103881836,
      "rot_rect_h_px": 5.81377649307251,
      "rot_rect_w_mm": 0.014758047103881835,
      "rot_rect_h_mm": 0.00581377649307251,
      "rot_rect_angle": -26.565052032470703,
      "solidity": 0.8723404255319149,
      "convexity": 0.9398501640653698,
      "circularity": 0.5025975218507402,
      "elongation": 0.39393941841690566,
      "aspect_ratio": 2.538461380733677,
      "eccentricity": 0.9424002371214837,
      "extent": 0.384375,
      "fill_ratio": 0.7167833225780539,
      "equivalent_diameter_px": 8.848967849484623,
      "equivalent_diameter_mm": 0.008848967849484623,
      "feret_max_px": 16.840164184570312,
      "feret_max_mm": 0.01684016418457031,
      "feret_min_px": 5.632822036743164,
      "feret_min_mm": 0.005632822036743164,
      "centroid_x": 10.794037940379402,
      "centroid_y": 639.1327913279132,
      "orientation_angle": 66.39891052246094,
      "hu_moments": [
        0.24547036527544952,
        0.046935277213408795,
        0.0013094506572387341,
        0.0003872299461797658,
        2.709499869757518e-07,
        8.141258651543112e-05,
        -5.207696308798737e-08
      ],
      "zernike_moments": [
        1.0,
        0.491267680485558,
        0.29513669605230824,
        0.1995703658001113,
        0.14557335532561505
      ]
    },
    {
      "label": 3,
      "area_px": 67.0,
      "area_mm2": 6.7e-05,
      "hull_area_px": 75.0,
      "hull_area_mm2": 7.5e-05,
      "perimeter_px": 42.28427076339722,
      "perimeter_mm": 0.04228427076339722,
      "hull_perimeter_px": 40.20911180973053,
      "hull_perimeter_mm": 0.04020911180973053,
      "length_px": 17.3648624420166,
      "length_mm": 0.017364862442016602,
      "width_px": 4.8373541831970215,
      "width_mm": 0.004837354183197021,
      "major_axis_px": 17.3648624420166,
      "major_axis_mm": 0.017364862442016602,
      "minor_axis_px": 4.8373541831970215,
      "minor_axis_mm": 0.004837354183197021,
      "bbox_x": 90,
      "bbox_y": 367,
      "bbox_w_px": 17,
      "bbox_h_px": 12,
      "bbox_w_mm": 0.017,
      "bbox_h_mm": 0.012,
      "rot_rect_w_px": 4.8373541831970215,
      "rot_rect_h_px": 17.3648624420166,
      "rot_rect_w_mm": 0.004837354183197021,
      "rot_rect_h_mm": 0.017364862442016602,
      "rot_rect_angle": -60.25511932373047,
      "solidity": 0.8933333333333333,
      "convexity": 0.9509236196769646,
      "circularity": 0.47089814156148174,
      "elongation": 0.27857140817265547,
      "aspect_ratio": 3.589743852607483,
      "eccentricity": 0.9793191380518942,
      "extent": 0.3284313725490196,
      "fill_ratio": 0.7976191428155583,
      "equivalent_diameter_px": 9.23618154310838,
      "equivalent_diameter_mm": 0.009236181543108379,
      "feret_max_px": 22.768413543701172,
      "feret_max_mm": 0.022768413543701172,
      "feret_min_px": 4.606541633605957,
      "feret_min_mm": 0.004606541633605957,
      "centroid_x": 98.05970149253731,
      "centroid_y": 372.2910447761194,
      "orientation_angle": 119.61306762695312,
      "hu_moments": [
        0.30620829803829075,
        0.09609175345711969,
        4.663175133636883e-05,
        4.8959952291993566e-06,
        -6.395005489629688e-11,
        -1.3425754202098474e-06,
        -3.7192695709608134e-11
      ],
      "zernike_moments": [
        1.0,
        0.5271560004297642,
        0.3468242595752261,
        0.2570885315841892,
        0.20429425867567266
      ]
    }
  ],
  "statistics": {
    "total_grains": 3,
    "per_metric": {
      "area_px": {
        "count": 3,
        "mean": 63.5,
        "median": 62.0,
        "mode": 61.5,
        "min": 61.5,
        "max": 67.0,
        "range": 5.5,
        "variance": 9.25,
        "std_dev": 3.0413812651491097,
        "cv": 4.789576795510409,
        "q1": 61.75,
        "q3": 64.5,
        "iqr": 2.75,
        "p5": 61.55,
        "p10": 61.6,
        "p90": 66.0,
        "p95": 66.5,
        "skewness": 0.6856675374889221,
        "kurtosis": 0.0,
        "ci_95_lower": 55.94479010343217,
        "ci_95_upper": 71.05520989656783,
        "shapiro_stat": 0.8175675675675674,
        "shapiro_p": 0.15716679846494003,
        "is_normal": true,
        "outliers": {
          "iqr_outliers": [],
          "zscore_outliers": []
        }
      },
      "perimeter_px": {
        "count": 3,
        "mean": 37.213203032811485,
        "median": 39.21320307254791,
        "mode": 30.14213526248932,
        "min": 30.14213526248932,
        "max": 42.28427076339722,
        "range": 12.142135500907898,
        "variance": 39.85786374981126,
        "std_dev": 6.313308463065246,
        "cv": 16.965238003024623,
        "q1": 34.677669167518616,
        "q3": 40.748736917972565,
        "iqr": 6.071067750453949,
        "p5": 31.049242043495177,
        "p10": 31.95634882450104,
        "p90": 41.67005722522735,
        "p95": 41.977163994312285,
        "skewness": -0.5235766575327603,
        "kurtosis": 0.0,
        "ci_95_lower": 21.53007539379859,
        "ci_95_upper": 52.89633067182438,
        "shapiro_stat": 0.9247325411607513,
        "shapiro_p": 0.46922560622146176,
        "is_normal": true,
        "outliers": {
          "iqr_outliers": [],
          "zscore_outliers": []
        }
      },
      "length_px": {
        "count": 3,
        "mean": 14.040969848632812,
        "median": 14.758047103881836,
        "mode": 10.0,
        "min": 10.0,
        "max": 17.3648624420166,
        "range": 7.364862442016602,
        "variance": 13.94594953995329,
        "std_dev": 3.7344276053972836,
        "cv": 26.596649986830574,
        "q1": 12.379023551940918,
        "q3": 16.06145477294922,
        "iqr": 3.682431221008301,
        "p5": 10.475804710388184,
        "p10": 10.951609420776368,
        "p90": 16.843499374389648,
        "p95": 17.104180908203126,
        "skewness": -0.339752994817437,
        "kurtosis": 0.0,
        "ci_95_lower": 4.764137402263939,
        "ci_95_upper": 23.317802295001684,
        "shapiro_stat": 0.9723468207459255,
        "shapiro_p": 0.680922539935065,
        "is_normal": true,
        "outliers": {
          "iqr_outliers": [],
          "zscore_outliers": []
        }
      },
      "width_px": {
        "count": 3,
        "mean": 6.217043558756511,
        "median": 5.81377649307251,
        "mode": 4.8373541831970215,
        "min": 4.8373541831970215,
        "max": 8.0,
        "range": 3.1626458168029785,
        "variance": 2.622550385334383,
        "std_dev": 1.6194290306569112,
        "cv": 26.048217538640152,
        "q1": 5.325565338134766,
        "q3": 6.906888246536255,
        "iqr": 1.5813229084014893,
        "p5": 4.93499641418457,
        "p10": 5.032638645172119,
        "p90": 7.562755298614502,
        "p95": 7.781377649307251,
        "skewness": 0.42910733257202954,
        "kurtosis": 0.0,
        "ci_95_lower": 2.1941588321983962,
        "ci_95_upper": 10.239928285314626,
        "shapiro_stat": 0.9534925066145155,
        "shapiro_p": 0.5848662029195218,
        "is_normal": true,
        "outliers": {
          "iqr_outliers": [],
          "zscore_outliers": []
        }
      },
      "major_axis_px": {
        "count": 3,
        "mean": 14.040969848632812,
        "median": 14.758047103881836,
        "mode": 10.0,
        "min": 10.0,
        "max": 17.3648624420166,
        "range": 7.364862442016602,
        "variance": 13.94594953995329,
        "std_dev": 3.7344276053972836,
        "cv": 26.596649986830574,
        "q1": 12.379023551940918,
        "q3": 16.06145477294922,
        "iqr": 3.682431221008301,
        "p5": 10.475804710388184,
        "p10": 10.951609420776368,
        "p90": 16.843499374389648,
        "p95": 17.104180908203126,
        "skewness": -0.339752994817437,
        "kurtosis": 0.0,
        "ci_95_lower": 4.764137402263939,
        "ci_95_upper": 23.317802295001684,
        "shapiro_stat": 0.9723468207459255,
        "shapiro_p": 0.680922539935065,
        "is_normal": true,
        "outliers": {
          "iqr_outliers": [],
          "zscore_outliers": []
        }
      },
      "minor_axis_px": {
        "count": 3,
        "mean": 6.217043558756511,
        "median": 5.81377649307251,
        "mode": 4.8373541831970215,
        "min": 4.8373541831970215,
        "max": 8.0,
        "range": 3.1626458168029785,
        "variance": 2.622550385334383,
        "std_dev": 1.6194290306569112,
        "cv": 26.048217538640152,
        "q1": 5.325565338134766,
        "q3": 6.906888246536255,
        "iqr": 1.5813229084014893,
        "p5": 4.93499641418457,
        "p10": 5.032638645172119,
        "p90": 7.562755298614502,
        "p95": 7.781377649307251,
        "skewness": 0.42910733257202954,
        "kurtosis": 0.0,
        "ci_95_lower": 2.1941588321983962,
        "ci_95_upper": 10.239928285314626,
        "shapiro_stat": 0.9534925066145155,
        "shapiro_p": 0.5848662029195218,
        "is_normal": true,
        "outliers": {
          "iqr_outliers": [],
          "zscore_outliers": []
        }
      },
      "equivalent_diameter_px": {
        "count": 3,
        "mean": 8.990005279724654,
        "median": 8.884866446580956,
        "mode": 8.848967849484623,
        "min": 8.848967849484623,
        "max": 9.23618154310838,
        "range": 0.3872136936237567,
        "variance": 0.04577424180855175,
        "std_dev": 0.21394915706436365,
        "cv": 2.379855744321837,
        "q1": 8.86691714803279,
        "q3": 9.060523994844669,
        "iqr": 0.19360684681187834,
        "p5": 8.852557709194256,
        "p10": 8.85614756890389,
        "p90": 9.165918523802896,
        "p95": 9.201050033455637,
        "skewness": 0.684776525183387,
        "kurtosis": 0.0,
        "ci_95_lower": 8.458526110263874,
        "ci_95_upper": 9.521484449185435,
        "shapiro_stat": 0.8188800000054893,
        "shapiro_p": 0.1604165068897474,
        "is_normal": true,
        "outliers": {
          "iqr_outliers": [],
          "zscore_outliers": []
        }
      },
      "feret_max_px": {
        "count": 3,
        "mean": 16.65856870015462,
        "median": 16.840164184570312,
        "mode": 10.367128372192383,
        "min": 10.367128372192383,
        "max": 22.768413543701172,
        "range": 12.401285171508789,
        "variance": 38.47270116624107,
        "std_dev": 6.202636630195346,
        "cv": 37.233910918996145,
        "q1": 13.603646278381348,
        "q3": 19.804288864135742,
        "iqr": 6.2006425857543945,
        "p5": 11.014431953430176,
        "p10": 11.661735534667969,
        "p90": 21.582763671875,
        "p95": 22.175588607788086,
        "skewness": -0.05373944519011649,
        "kurtosis": 0.0,
        "ci_95_lower": 1.2503651348023777,
        "ci_95_upper": 32.06677226550686,
        "shapiro_stat": 0.9993571366392171,
        "shapiro_p": 0.9515708041437332,
        "is_normal": true,
        "outliers": {
          "iqr_outliers": [],
          "zscore_outliers": []
        }
      },
      "feret_min_px": {
        "count": 3,
        "mean": 6.296485265096028,
        "median": 5.632822036743164,
        "mode": 4.606541633605957,
        "min": 4.606541633605957,
        "max": 8.650092124938965,
        "range": 4.043550491333008,
        "variance": 4.417911804490662,
        "std_dev": 2.1018829188350767,
        "cv": 33.381844478961405,
        "q1": 5.1196818351745605,
        "q3": 7.1414570808410645,
        "iqr": 2.021775245666504,
        "p5": 4.709169673919678,
        "p10": 4.811797714233398,
        "p90": 8.046638107299804,
        "p95": 8.348365116119384,
        "skewness": 0.5222340940671282,
        "kurtosis": 0.0,
        "ci_95_lower": 1.0751186407339555,
        "ci_95_upper": 11.5178518894581,
        "shapiro_stat": 0.9252278734570859,
        "shapiro_p": 0.4710212262516774,
        "is_normal": true,
        "outliers": {
          "iqr_outliers": [],
          "zscore_outliers": []
        }
      },
      "solidity": {
        "count": 3,
        "mean": 0.9140172372070513,
        "median": 0.8933333333333333,
        "mode": 0.8723404255319149,
        "min": 0.8723404255319149,
        "max": 0.9763779527559056,
        "range": 0.10403752722399062,
        "variance": 0.0030268196773135508,
        "std_dev": 0.05501654003400751,
        "cv": 6.019201585532535,
        "q1": 0.8828368794326241,
        "q3": 0.9348556430446194,
        "iqr": 0.05201876361199531,
        "p5": 0.8744397163120567,
        "p10": 0.8765390070921986,
        "p90": 0.9597690288713911,
        "p95": 0.9680734908136484,
        "skewness": 0.5930552484479622,
        "kurtosis": 0.0,
        "ci_95_lower": 0.7773485753385515,
        "ci_95_upper": 1.0506858990755512,
        "shapiro_stat": 0.8939917326433896,
        "shapiro_p": 0.3666243419671813,
        "is_normal": true,
        "outliers": {
          "iqr_outliers": [],
          "zscore_outliers": []
        }
      },
      "convexity": {
        "count": 3,
        "mean": 0.957681078498668,
        "median": 0.9509236196769646,
        "mode": 0.9398501640653698,
        "min": 0.9398501640653698,
        "max": 0.9822694517536696,
        "range": 0.042419287688299834,
        "variance": 0.0004840964292909495,
        "std_dev": 0.02200219146564609,
        "cv": 2.2974445208981633,
        "q1": 0.9453868918711672,
        "q3": 0.9665965357153171,
        "iqr": 0.021209643844149917,
        "p5": 0.9409575096265292,
        "p10": 0.9420648551876888,
        "p90": 0.9760002853383286,
        "p95": 0.9791348685459992,
        "skewness": 0.511005871954307,
        "kurtosis": 0.0,
        "ci_95_lower": 0.9030246049377053,
        "ci_95_upper": 1.0123375520596307,
        "shapiro_stat": 0.9292549268635903,
        "shapiro_p": 0.48582798042503567,
        "is_normal": true,
        "outliers": {
          "iqr_outliers": [],
          "zscore_outliers": []
        }
      },
      "circularity": {
        "count": 3,
        "mean": 0.6103446536813656,
        "median": 0.5025975218507402,
        "mode": 0.47089814156148174,
        "min": 0.47089814156148174,
        "max": 0.8575382976318751,
        "range": 0.3866401560703933,
        "variance": 0.04607973588482916,
        "std_dev": 0.21466191065214424,
        "cv": 35.17060555169701,
        "q1": 0.486747831706111,
        "q3": 0.6800679097413076,
        "iqr": 0.19332007803519657,
        "p5": 0.4740680795904076,
        "p10": 0.47723801761933343,
        "p90": 0.7865501424756481,
        "p95": 0.8220442200537615,
        "skewness": 0.6897990481792307,
        "kurtosis": 0.0,
        "ci_95_lower": 0.07709490615399417,
        "ci_95_upper": 1.1435944012087371,
        "shapiro_stat": 0.8110431158924837,
        "shapiro_p": 0.14114404562131336,
        "is_normal": true,
        "outliers": {
          "iqr_outliers": [],
          "zscore_outliers": []
        }
      },
      "elongation": {
        "count": 3,
        "mean": 0.49083694219652035,
        "median": 0.39393941841690566,
        "mode": 0.27857140817265547,
        "min": 0.27857140817265547,
        "max": 0.8,
        "range": 0.5214285918273446,
        "variance": 0.07501379167972763,
        "std_dev": 0.27388645764208136,
        "cv": 55.799886702990506,
        "q1": 0.3362554132947806,
        "q3": 0.5969697092084528,
        "iqr": 0.26071429591367223,
        "p5": 0.29010820919708047,
        "p10": 0.3016450102215055,
        "p90": 0.7187878836833812,
        "p95": 0.7593939418416906,
        "skewness": 0.5685975276593925,
        "kurtosis": 0.0,
        "ci_95_lower": -0.1895347359698833,
        "ci_95_upper": 1.171208620362924,
        "shapiro_stat": 0.9061259612628165,
        "shapiro_p": 0.4052756245602567,
        "is_normal": true,
        "outliers": {
          "iqr_outliers": [],
          "zscore_outliers": []
        }
      },
      "aspect_ratio": {
        "count": 3,
        "mean": 2.4594017444470535,
        "median": 2.538461380733677,
        "mode": 1.25,
        "min": 1.25,
        "max": 3.589743852607483,
        "range": 2.339743852607483,
        "variance": 1.373288143520957,
        "std_dev": 1.171873774568301,
        "cv": 47.64873316098965,
        "q1": 1.8942306903668384,
        "q3": 3.06410261667058,
        "iqr": 1.1698719263037416,
        "p5": 1.3788461380733676,
        "p10": 1.5076922761467353,
        "p90": 3.379487358232722,
        "p95": 3.4846156054201023,
        "skewness": -0.12337571768959109,
        "kurtosis": 0.0,
        "ci_95_lower": -0.4516940923692676,
        "ci_95_upper": 5.370497581263375,
        "shapiro_stat": 0.9965864268256835,
        "shapiro_p": 0.8883513750641291,
        "is_normal": true,
        "outliers": {
          "iqr_outliers": [],
          "zscore_outliers": []
        }
      },
      "eccentricity": {
        "count": 3,
        "mean": 0.8243045831845616,
        "median": 0.9424002371214837,
        "mode": 0.5511943743803066,
        "min": 0.5511943743803066,
        "max": 0.9793191380518942,
        "range": 0.4281247636715876,
        "variance": 0.056282640926305146,
        "std_dev": 0.23723962764745932,
        "cv": 28.78057850059793,
        "q1": 0.7467973057508952,
        "q3": 0.9608596875866889,
        "iqr": 0.21406238183579374,
        "p5": 0.5903149606544243,
        "p10": 0.629435546928542,
        "p90": 0.9719353578658121,
        "p95": 0.9756272479588531,
        "skewness": -0.6878908212638914,
        "kurtosis": 0.0,
        "ci_95_lower": 0.2349686774239016,
        "ci_95_upper": 1.4136404889452217,
        "shapiro_stat": 0.8141533972652794,
        "shapiro_p": 0.14875518486760428,
        "is_normal": true,
        "outliers": {
          "iqr_outliers": [],
          "zscore_outliers": []
        }
      },
      "extent": {
        "count": 3,
        "mean": 0.44635633293721527,
        "median": 0.384375,
        "mode": 0.3284313725490196,
        "min": 0.3284313725490196,
        "max": 0.6262626262626263,
        "range": 0.2978312537136067,
        "variance": 0.025057128146660137,
        "std_dev": 0.15829443498323034,
        "cv": 35.46369196592,
        "q1": 0.35640318627450984,
        "q3": 0.5053188131313131,
        "iqr": 0.14891562685680326,
        "p5": 0.33402573529411766,
        "p10": 0.33962009803921567,
        "p90": 0.577885101010101,
        "p95": 0.6020738636363636,
        "skewness": 0.6090500090335855,
        "kurtosis": 0.0,
        "ci_95_lower": 0.05313115743516206,
        "ci_95_upper": 0.8395815084392685,
        "shapiro_stat": 0.8850121926327182,
        "shapiro_p": 0.33926797798180164,
        "is_normal": true,
        "outliers": {
          "iqr_outliers": [],
          "zscore_outliers": []
        }
      },
      "fill_ratio": {
        "count": 3,
        "mean": 0.7631341551312042,
        "median": 0.775,
        "mode": 0.7167833225780539,
        "min": 0.7167833225780539,
        "max": 0.7976191428155583,
        "range": 0.08083582023750446,
        "variance": 0.0017392061642052823,
        "std_dev": 0.04170379076541223,
        "cv": 5.464804646077226,
        "q1": 0.745891661289027,
        "q3": 0.7863095714077792,
        "iqr": 0.04041791011875229,
        "p5": 0.7226049903202485,
        "p10": 0.7284266580624431,
        "p90": 0.7930953142524467,
        "p95": 0.7953572285340025,
        "skewness": -0.4803928892008479,
        "kurtosis": 0.0,
        "ci_95_lower": 0.6595361957678985,
        "ci_95_upper": 0.8667321144945099,
        "shapiro_stat": 0.9392833880128291,
        "shapiro_p": 0.5244992473658437,
        "is_normal": true,
        "outliers": {
          "iqr_outliers": [],
          "zscore_outliers": []
        }
      },
      "orientation_angle": {
        "count": 3,
        "mean": 96.49703725179036,
        "median": 103.47913360595703,
        "mode": 66.39891052246094,
        "min": 66.39891052246094,
        "max": 119.61306762695312,
        "range": 53.21415710449219,
        "variance": 744.4988812095446,
        "std_dev": 27.285506797740528,
        "cv": 28.276004709392556,
        "q1": 84.93902206420898,
        "q3": 111.54610061645508,
        "iqr": 26.607078552246094,
        "p5": 70.10693283081055,
        "p10": 73.81495513916016,
        "p90": 116.3862808227539,
        "p95": 117.99967422485352,
        "skewness": -0.4393183817699183,
        "kurtosis": 0.0,
        "ci_95_lower": 28.71608083130313,
        "ci_95_upper": 164.2779936722776,
        "shapiro_stat": 0.9508901181090426,
        "shapiro_p": 0.5732177841718606,
        "is_normal": true,
        "outliers": {
          "iqr_outliers": [],
          "zscore_outliers": []
        }
      }
    },
    "correlation": {
      "area_px": {
        "area_px": 1.0,
        "perimeter_px": 0.6342,
        "length_px": 0.7158,
        "width_px": -0.6798,
        "major_axis_px": 0.7158,
        "minor_axis_px": -0.6798,
        "equivalent_diameter_px": 1.0,
        "feret_max_px": 0.8073,
        "feret_min_px": -0.6349,
        "solidity": -0.2468,
        "convexity": -0.1858,
        "circularity": -0.4927,
        "elongation": -0.608,
        "aspect_ratio": 0.7873,
        "eccentricity": 0.4962,
        "extent": -0.5802,
        "fill_ratio": 0.7711,
        "orientation_angle": 0.7871
      },
      "perimeter_px": {
        "area_px": 0.6342,
        "perimeter_px": 1.0,
        "length_px": 0.9939,
        "width_px": -0.9982,
        "major_axis_px": 0.9939,
        "minor_axis_px": -0.9982,
        "equivalent_diameter_px": 0.6329,
        "feret_max_px": 0.9683,
        "feret_min_px": -1.0,
        "solidity": -0.9058,
        "convexity": -0.8776,
        "circularity": -0.9853,
        "elongation": -0.9994,
        "aspect_ratio": 0.976,
        "eccentricity": 0.986,
        "extent": -0.9977,
        "fill_ratio": -0.0033,
        "orientation_angle": 0.0222
      },
      "length_px": {
        "area_px": 0.7158,
        "perimeter_px": 0.9939,
        "length_px": 1.0,
        "width_px": -0.9987,
        "major_axis_px": 1.0,
        "minor_axis_px": -0.9987,
        "equivalent_diameter_px": 0.7147,
        "feret_max_px": 0.99,
        "feret_min_px": -0.994,
        "solidity": -0.8533,
        "convexity": -0.8191,
        "circularity": -0.9603,
        "elongation": -0.9896,
        "aspect_ratio": 0.9941,
        "eccentricity": 0.9614,
        "extent": -0.984,
        "fill_ratio": 0.1074,
        "orientation_angle": 0.1327
      },
      "width_px": {
        "area_px": -0.6798,
        "perimeter_px": -0.9982,
        "length_px": -0.9987,
        "width_px": 1.0,
        "major_axis_px": -0.9987,
        "minor_axis_px": 1.0,
        "equivalent_diameter_px": -0.6786,
        "feret_max_px": -0.9816,
        "feret_min_px": 0.9982,
        "solidity": 0.8784,
        "convexity": 0.8469,
        "circularity": 0.9731,
        "elongation": 0.9956,
        "aspect_ratio": -0.9874,
        "eccentricity": -0.974,
        "extent": 0.9917,
        "fill_ratio": -0.0572,
        "orientation_angle": -0.0827
      },
      "major_axis_px": {
        "area_px": 0.7158,
        "perimeter_px": 0.9939,
        "length_px": 1.0,
        "width_px": -0.9987,
        "major_axis_px": 1.0,
        "minor_axis_px": -0.9987,
        "equivalent_diameter_px": 0.7147,
        "feret_max_px": 0.99,
        "feret_min_px": -0.994,
        "solidity": -0.8533,
        "convexity": -0.8191,
        "circularity": -0.9603,
        "elongation": -0.9896,
        "aspect_ratio": 0.9941,
        "eccentricity": 0.9614,
        "extent": -0.984,
        "fill_ratio": 0.1074,
        "orientation_angle": 0.1327
      },
      "minor_axis_px": {
        "area_px": -0.6798,
        "perimeter_px": -0.9982,
        "length_px": -0.9987,
        "width_px": 1.0,
        "major_axis_px": -0.9987,
        "minor_axis_px": 1.0,
        "equivalent_diameter_px": -0.6786,
        "feret_max_px": -0.9816,
        "feret_min_px": 0.9982,
        "solidity": 0.8784,
        "convexity": 0.8469,
        "circularity": 0.9731,
        "elongation": 0.9956,
        "aspect_ratio": -0.9874,
        "eccentricity": -0.974,
        "extent": 0.9917,
        "fill_ratio": -0.0572,
        "orientation_angle": -0.0827
      },
      "equivalent_diameter_px": {
        "area_px": 1.0,
        "perimeter_px": 0.6329,
        "length_px": 0.7147,
        "width_px": -0.6786,
        "major_axis_px": 0.7147,
        "minor_axis_px": -0.6786,
        "equivalent_diameter_px": 1.0,
        "feret_max_px": 0.8063,
        "feret_min_px": -0.6336,
        "solidity": -0.2451,
        "convexity": -0.1842,
        "circularity": -0.4912,
        "elongation": -0.6066,
        "aspect_ratio": 0.7863,
        "eccentricity": 0.4947,
        "extent": -0.5788,
        "fill_ratio": 0.7722,
        "orientation_angle": 0.7881
      },
      "feret_max_px": {
        "area_px": 0.8073,
        "perimeter_px": 0.9683,
        "length_px": 0.99,
        "width_px": -0.9816,
        "major_axis_px": 0.99,
        "minor_axis_px": -0.9816,
        "equivalent_diameter_px": 0.8063,
        "feret_max_px": 1.0,
        "feret_min_px": -0.9685,
        "solidity": -0.7711,
        "convexity": -0.7299,
        "circularity": -0.9113,
        "elongation": -0.9594,
        "aspect_ratio": 0.9995,
        "eccentricity": 0.9129,
        "extent": -0.949,
        "fill_ratio": 0.2467,
        "orientation_angle": 0.2713
      },
      "feret_min_px": {
        "area_px": -0.6349,
        "perimeter_px": -1.0,
        "length_px": -0.994,
        "width_px": 0.9982,
        "major_axis_px": -0.994,
        "minor_axis_px": 0.9982,
        "equivalent_diameter_px": -0.6336,
        "feret_max_px": -0.9685,
        "feret_min_px": 1.0,
        "solidity": 0.9054,
        "convexity": 0.8771,
        "circularity": 0.9851,
        "elongation": 0.9994,
        "aspect_ratio": -0.9762,
        "eccentricity": -0.9858,
        "extent": 0.9976,
        "fill_ratio": 0.0023,
        "orientation_angle": -0.0232
      },
      "solidity": {
        "area_px": -0.2468,
        "perimeter_px": -0.9058,
        "length_px": -0.8533,
        "width_px": 0.8784,
        "major_axis_px": -0.8533,
        "minor_axis_px": 0.8784,
        "equivalent_diameter_px": -0.2451,
        "feret_max_px": -0.7711,
        "feret_min_px": 0.9054,
        "solidity": 1.0,
        "convexity": 0.9981,
        "circularity": 0.9649,
        "elongation": 0.9194,
        "aspect_ratio": -0.7918,
        "eccentricity": -0.9638,
        "extent": 0.9325,
        "fill_ratio": 0.4268,
        "orientation_angle": 0.4036
      },
      "convexity": {
        "area_px": -0.1858,
        "perimeter_px": -0.8776,
        "length_px": -0.8191,
        "width_px": 0.8469,
        "major_axis_px": -0.8191,
        "minor_axis_px": 0.8469,
        "equivalent_diameter_px": -0.1842,
        "feret_max_px": -0.7299,
        "feret_min_px": 0.8771,
        "solidity": 0.9981,
        "convexity": 1.0,
        "circularity": 0.9466,
        "elongation": 0.8931,
        "aspect_ratio": -0.7521,
        "eccentricity": -0.9453,
        "extent": 0.9081,
        "fill_ratio": 0.4824,
        "orientation_angle": 0.4599
      },
      "circularity": {
        "area_px": -0.4927,
        "perimeter_px": -0.9853,
        "length_px": -0.9603,
        "width_px": 0.9731,
        "major_axis_px": -0.9603,
        "minor_axis_px": 0.9731,
        "equivalent_diameter_px": -0.4912,
        "feret_max_px": -0.9113,
        "feret_min_px": 0.9851,
        "solidity": 0.9649,
        "convexity": 0.9466,
        "circularity": 1.0,
        "elongation": 0.9905,
        "aspect_ratio": -0.9244,
        "eccentricity": -1.0,
        "extent": 0.9946,
        "fill_ratio": 0.1742,
        "orientation_angle": 0.149
      },
      "elongation": {
        "area_px": -0.608,
        "perimeter_px": -0.9994,
        "length_px": -0.9896,
        "width_px": 0.9956,
        "major_axis_px": -0.9896,
        "minor_axis_px": 0.9956,
        "equivalent_diameter_px": -0.6066,
        "feret_max_px": -0.9594,
        "feret_min_px": 0.9994,
        "solidity": 0.9194,
        "convexity": 0.8931,
        "circularity": 0.9905,
        "elongation": 1.0,
        "aspect_ratio": -0.9682,
        "eccentricity": -0.991,
        "extent": 0.9994,
        "fill_ratio": 0.0368,
        "orientation_angle": 0.0113
      },
      "aspect_ratio": {
        "area_px": 0.7873,
        "perimeter_px": 0.976,
        "length_px": 0.9941,
        "width_px": -0.9874,
        "major_axis_px": 0.9941,
        "minor_axis_px": -0.9874,
        "equivalent_diameter_px": 0.7863,
        "feret_max_px": 0.9995,
        "feret_min_px": -0.9762,
        "solidity": -0.7918,
        "convexity": -0.7521,
        "circularity": -0.9244,
        "elongation": -0.9682,
        "aspect_ratio": 1.0,
        "eccentricity": 0.926,
        "extent": -0.959,
        "fill_ratio": 0.2145,
        "orientation_angle": 0.2393
      },
      "eccentricity": {
        "area_px": 0.4962,
        "perimeter_px": 0.986,
        "length_px": 0.9614,
        "width_px": -0.974,
        "major_axis_px": 0.9614,
        "minor_axis_px": -0.974,
        "equivalent_diameter_px": 0.4947,
        "feret_max_px": 0.9129,
        "feret_min_px": -0.9858,
        "solidity": -0.9638,
        "convexity": -0.9453,
        "circularity": -1.0,
        "elongation": -0.991,
        "aspect_ratio": 0.926,
        "eccentricity": 1.0,
        "extent": -0.995,
        "fill_ratio": -0.1703,
        "orientation_angle": -0.1451
      },
      "extent": {
        "area_px": -0.5802,
        "perimeter_px": -0.9977,
        "length_px": -0.984,
        "width_px": 0.9917,
        "major_axis_px": -0.984,
        "minor_axis_px": 0.9917,
        "equivalent_diameter_px": -0.5788,
        "feret_max_px": -0.949,
        "feret_min_px": 0.9976,
        "solidity": 0.9325,
        "convexity": 0.9081,
        "circularity": 0.9946,
        "elongation": 0.9994,
        "aspect_ratio": -0.959,
        "eccentricity": -0.995,
        "extent": 1.0,
        "fill_ratio": 0.0713,
        "orientation_angle": 0.0458
      },
      "fill_ratio": {
        "area_px": 0.7711,
        "perimeter_px": -0.0033,
        "length_px": 0.1074,
        "width_px": -0.0572,
        "major_axis_px": 0.1074,
        "minor_axis_px": -0.0572,
        "equivalent_diameter_px": 0.7722,
        "feret_max_px": 0.2467,
        "feret_min_px": 0.0023,
        "solidity": 0.4268,
        "convexity": 0.4824,
        "circularity": 0.1742,
        "elongation": 0.0368,
        "aspect_ratio": 0.2145,
        "eccentricity": -0.1703,
        "extent": 0.0713,
        "fill_ratio": 1.0,
        "orientation_angle": 0.9997
      },
      "orientation_angle": {
        "area_px": 0.7871,
        "perimeter_px": 0.0222,
        "length_px": 0.1327,
        "width_px": -0.0827,
        "major_axis_px": 0.1327,
        "minor_axis_px": -0.0827,
        "equivalent_diameter_px": 0.7881,
        "feret_max_px": 0.2713,
        "feret_min_px": -0.0232,
        "solidity": 0.4036,
        "convexity": 0.4599,
        "circularity": 0.149,
        "elongation": 0.0113,
        "aspect_ratio": 0.2393,
        "eccentricity": -0.1451,
        "extent": 0.0458,
        "fill_ratio": 0.9997,
        "orientation_angle": 1.0
      }
    },
    "mm_stats": {
      "length_mm": {
        "count": 3,
        "mean": 0.014040969848632812,
        "median": 0.014758047103881835,
        "mode": 0.01,
        "min": 0.01,
        "max": 0.017364862442016602,
        "range": 0.007364862442016602,
        "variance": 1.394594953995329e-05,
        "std_dev": 0.0037344276053972838,
        "cv": 26.596649986830574,
        "q1": 0.012379023551940918,
        "q3": 0.016061454772949218,
        "iqr": 0.0036824312210083,
        "p5": 0.010475804710388184,
        "p10": 0.010951609420776368,
        "p90": 0.01684349937438965,
        "p95": 0.017104180908203124,
        "skewness": -0.3397529948174362,
        "kurtosis": 0.0,
        "ci_95_lower": 0.004764137402263939,
        "ci_95_upper": 0.023317802295001685,
        "shapiro_stat": 0.9723468207459258,
        "shapiro_p": 0.6809225399350676,
        "is_normal": true
      },
      "width_mm": {
        "count": 3,
        "mean": 0.006217043558756511,
        "median": 0.00581377649307251,
        "mode": 0.004837354183197021,
        "min": 0.004837354183197021,
        "max": 0.008,
        "range": 0.003162645816802979,
        "variance": 2.6225503853343836e-06,
        "std_dev": 0.0016194290306569114,
        "cv": 26.048217538640152,
        "q1": 0.005325565338134766,
        "q3": 0.006906888246536255,
        "iqr": 0.001581322908401489,
        "p5": 0.00493499641418457,
        "p10": 0.005032638645172119,
        "p90": 0.007562755298614502,
        "p95": 0.007781377649307251,
        "skewness": 0.4291073325720289,
        "kurtosis": 0.0,
        "ci_95_lower": 0.002194158832198396,
        "ci_95_upper": 0.010239928285314625,
        "shapiro_stat": 0.9534925066145155,
        "shapiro_p": 0.5848662029195218,
        "is_normal": true
      },
      "area_mm2": {
        "count": 3,
        "mean": 6.350000000000001e-05,
        "median": 6.2e-05,
        "mode": 6.15e-05,
        "min": 6.15e-05,
        "max": 6.7e-05,
        "range": 5.499999999999998e-06,
        "variance": 9.249999999999996e-12,
        "std_dev": 3.041381265149109e-06,
        "cv": 4.789576795510407,
        "q1": 6.175000000000001e-05,
        "q3": 6.45e-05,
        "iqr": 2.7499999999999855e-06,
        "p5": 6.155e-05,
        "p10": 6.16e-05,
        "p90": 6.6e-05,
        "p95": 6.65e-05,
        "skewness": 0.6856675374889114,
        "kurtosis": 0.0,
        "ci_95_lower": 5.594479010343218e-05,
        "ci_95_upper": 7.105520989656785e-05,
        "shapiro_stat": 0.8175675675675674,
        "shapiro_p": 0.15716679846494003,
        "is_normal": true
      },
      "perimeter_mm": {
        "count": 3,
        "mean": 0.03721320303281148,
        "median": 0.039213203072547914,
        "mode": 0.03014213526248932,
        "min": 0.03014213526248932,
        "max": 0.04228427076339722,
        "range": 0.0121421355009079,
        "variance": 3.985786374981128e-05,
        "std_dev": 0.006313308463065248,
        "cv": 16.96523800302463,
        "q1": 0.03467766916751862,
        "q3": 0.04074873691797257,
        "iqr": 0.006071067750453948,
        "p5": 0.031049242043495177,
        "p10": 0.03195634882450104,
        "p90": 0.04167005722522736,
        "p95": 0.04197716399431229,
        "skewness": -0.5235766575327582,
        "kurtosis": 0.0,
        "ci_95_lower": 0.021530075393798587,
        "ci_95_upper": 0.05289633067182438,
        "shapiro_stat": 0.9247325411607517,
        "shapiro_p": 0.46922560622146325,
        "is_normal": true
      }
    },
    "calibrated": true,
    "pixels_per_mm": 1000.0
  },
  "quality": {
    "total_grains": 3,
    "broken_pct": 0.0,
    "abnormal_pct": 33.33333333333333,
    "size_distribution": {
      "length_mean": 14.040969848632812,
      "length_std": 3.0491473715289974,
      "width_mean": 6.217043558756511,
      "width_std": 1.3222582665864695,
      "area_mean": 63.5,
      "area_std": 2.48327740429189
    },
    "size_category_counts": {
      "long_grain": 0,
      "medium_grain": 0,
      "short_grain": 3
    },
    "uniformity_index": 78.28392622162139,
    "cv_length": 21.716073778378615,
    "cv_area": 3.910673077625024,
    "average_aspect_ratio": 2.4594017444470535,
    "shape_consistency": 71.2833208178817,
    "grain_density": 0.0002723794381405564,
    "packing_ratio": 0.0002723794381405564,
    "avg_inter_grain_spacing_px": 474.8673773123465,
    "orientation": {
      "mean": 96.49703725179036,
      "std": 22.278523009235368,
      "circular_mean": 96.7584270400584,
      "circular_std": 22.49378763059696
    }
  },
  "classifications": [
    {
      "label": 1,
      "categories": [
        "short_grain",
        "whole_grain"
      ],
      "primary_category": "short_grain"
    },
    {
      "label": 2,
      "categories": [
        "short_grain",
        "whole_grain"
      ],
      "primary_category": "short_grain"
    },
    {
      "label": 3,
      "categories": [
        "short_grain",
        "whole_grain",
        "abnormal_grain"
      ],
      "primary_category": "abnormal_grain"
    }
  ],
  "grading": {
    "grade": "Reject",
    "grade_key": "reject",
    "explanation": "Sample classified as **Reject**.\n  \u2022 broken_pct: 0.00 <= 100.00 \u2192 PASS\n  \u2022 uniformity_index: 78.28 >= 0.00 \u2192 PASS\n  \u2022 abnormal_pct: 33.33 <= 100.00 \u2192 PASS\n  \u2022 cv_length: 21.72 <= 100.00 \u2192 PASS\n  \u2022 Total grains: 3\n  \u2022 Broken: 0.00%\n  \u2022 Uniformity: 78.28%\n  \u2022 Abnormal: 33.33%",
    "criteria_results": [
      {
        "criterion": "broken_pct",
        "value": 0.0,
        "threshold": 100.0,
        "operator": "<=",
        "passed": true
      },
      {
        "criterion": "uniformity_index",
        "value": 78.28392622162139,
        "threshold": 0.0,
        "operator": ">=",
        "passed": true
      },
      {
        "criterion": "abnormal_pct",
        "value": 33.33333333333333,
        "threshold": 100.0,
        "operator": "<=",
        "passed": true
      },
      {
        "criterion": "cv_length",
        "value": 21.716073778378615,
        "threshold": 100.0,
        "operator": "<=",
        "passed": true
      }
    ],
    "all_evaluations": [
      {
        "grade": "premium",
        "label": "Premium",
        "all_passed": false,
        "checks": [
          {
            "criterion": "broken_pct",
            "value": 0.0,
            "threshold": 2.0,
            "operator": "<=",
            "passed": true
          },
          {
            "criterion": "uniformity_index",
            "value": 78.28392622162139,
            "threshold": 90.0,
            "operator": ">=",
            "passed": false
          },
          {
            "criterion": "abnormal_pct",
            "value": 33.33333333333333,
            "threshold": 1.0,
            "operator": "<=",
            "passed": false
          },
          {
            "criterion": "cv_length",
            "value": 21.716073778378615,
            "threshold": 10.0,
            "operator": "<=",
            "passed": false
          }
        ]
      },
      {
        "grade": "grade_a",
        "label": "Grade A",
        "all_passed": false,
        "checks": [
          {
            "criterion": "broken_pct",
            "value": 0.0,
            "threshold": 5.0,
            "operator": "<=",
            "passed": true
          },
          {
            "criterion": "uniformity_index",
            "value": 78.28392622162139,
            "threshold": 80.0,
            "operator": ">=",
            "passed": false
          },
          {
            "criterion": "abnormal_pct",
            "value": 33.33333333333333,
            "threshold": 3.0,
            "operator": "<=",
            "passed": false
          },
          {
            "criterion": "cv_length",
            "value": 21.716073778378615,
            "threshold": 15.0,
            "operator": "<=",
            "passed": false
          }
        ]
      },
      {
        "grade": "grade_b",
        "label": "Grade B",
        "all_passed": false,
        "checks": [
          {
            "criterion": "broken_pct",
            "value": 0.0,
            "threshold": 10.0,
            "operator": "<=",
            "passed": true
          },
          {
            "criterion": "uniformity_index",
            "value": 78.28392622162139,
            "threshold": 70.0,
            "operator": ">=",
            "passed": true
          },
          {
            "criterion": "abnormal_pct",
            "value": 33.33333333333333,
            "threshold": 5.0,
            "operator": "<=",
            "passed": false
          },
          {
            "criterion": "cv_length",
            "value": 21.716073778378615,
            "threshold": 20.0,
            "operator": "<=",
            "passed": false
          }
        ]
      },
      {
        "grade": "grade_c",
        "label": "Grade C",
        "all_passed": false,
        "checks": [
          {
            "criterion": "broken_pct",
            "value": 0.0,
            "threshold": 15.0,
            "operator": "<=",
            "passed": true
          },
          {
            "criterion": "uniformity_index",
            "value": 78.28392622162139,
            "threshold": 60.0,
            "operator": ">=",
            "passed": true
          },
          {
            "criterion": "abnormal_pct",
            "value": 33.33333333333333,
            "threshold": 8.0,
            "operator": "<=",
            "passed": false
          },
          {
            "criterion": "cv_length",
            "value": 21.716073778378615,
            "threshold": 25.0,
            "operator": "<=",
            "passed": true
          }
        ]
      },
      {
        "grade": "reject",
        "label": "Reject",
        "all_passed": true,
        "checks": [
          {
            "criterion": "broken_pct",
            "value": 0.0,
            "threshold": 100.0,
            "operator": "<=",
            "passed": true
          },
          {
            "criterion": "uniformity_index",
            "value": 78.28392622162139,
            "threshold": 0.0,
            "operator": ">=",
            "passed": true
          },
          {
            "criterion": "abnormal_pct",
            "value": 33.33333333333333,
            "threshold": 100.0,
            "operator": "<=",
            "passed": true
          },
          {
            "criterion": "cv_length",
            "value": 21.716073778378615,
            "threshold": 100.0,
            "operator": "<=",
            "passed": true
          }
        ]
      }
    ]
  }
}